horsetalk/__init__.py
horsetalk/age_category.py
horsetalk/age_restriction.py
horsetalk/aw_going_description.py
horsetalk/breed.py
horsetalk/coat_colour.py
horsetalk/country.py
horsetalk/dirt_going_description.py
horsetalk/disaster.py
horsetalk/draw.py
horsetalk/finishing_position.py
horsetalk/form_break.py
horsetalk/form_figures.py
horsetalk/gender.py
horsetalk/going.py
horsetalk/going_description.py
horsetalk/handedness.py
horsetalk/headgear.py
horsetalk/hemisphere.py
horsetalk/horse.py
horsetalk/horse_age.py
horsetalk/horse_experience_level.py
horsetalk/horse_height.py
horsetalk/horselength.py
horsetalk/jockey_experience_level.py
horsetalk/jump_category.py
horsetalk/obstacle_style.py
horsetalk/outcome.py
horsetalk/py.typed
horsetalk/quantity.py
horsetalk/race_class.py
horsetalk/race_conditions.py
horsetalk/race_designation.py
horsetalk/race_distance.py
horsetalk/race_distance_category.py
horsetalk/race_grade.py
horsetalk/race_level.py
horsetalk/race_performance.py
horsetalk/race_title.py
horsetalk/race_weight.py
horsetalk/racecourse.py
horsetalk/racecourse_contour.py
horsetalk/racecourse_shape.py
horsetalk/racecourse_style.py
horsetalk/racing_code.py
horsetalk/sex.py
horsetalk/silks.py
horsetalk/stalls_position.py
horsetalk/surface.py
horsetalk/turf_going_description.py
horsetalk-0.30.0.dist-info/LICENSE
horsetalk-0.30.0.dist-info/METADATA
horsetalk-0.30.0.dist-info/WHEEL
horsetalk-0.30.0.dist-info/RECORD
