Metadata-Version: 2.3
Name: horsetalk
Version: 0.30.0
Summary: A library of enums and parsers for common horseracing terminology
License: GPL-3.0-only
Author: peaky76
Author-email: robertjamespeacock@gmail.com
Requires-Python: >=3.11,<3.14
Classifier: License :: OSI Approved :: GNU General Public License v3 (GPLv3)
Classifier: Programming Language :: Python :: 3
Classifier: Programming Language :: Python :: 3.11
Classifier: Programming Language :: Python :: 3.12
Classifier: Programming Language :: Python :: 3.13
Requires-Dist: babel (>=2.17.0,<3.0.0)
Requires-Dist: peak-utility (>=0,<1)
Requires-Dist: pendulum (>=3.0.0,<4.0.0)
Requires-Dist: pint (>=0.23,<0.26)
